LICENSE
MANIFEST.in
README.rst
manage.py
setup.py
django_permissivecsrf.egg-info/PKG-INFO
django_permissivecsrf.egg-info/SOURCES.txt
django_permissivecsrf.egg-info/dependency_links.txt
django_permissivecsrf.egg-info/requires.txt
django_permissivecsrf.egg-info/top_level.txt
permissivecsrf/__init__.py
permissivecsrf/middleware.py
permissivecsrf/models.py
permissivecsrf/tests.py
permissivecsrf/views.py
test_project/__init__.py
test_project/settings.py
test_project/urls.py
test_project/wsgi.py