Metadata-Version: 1.0
Name: django-permissivecsrf
Version: 1.0.0
Summary: More permissive CSRF check for Django when moving between HTTP and HTTPS
Home-page: https://github.com/philipmat/django-permissivecsrf
Author: Philip Mateescu
Author-email: dev@philipm.at
License: BSD
Keywords: django,CSRF
Platform: any
Classifier: Development Status :: 5 - Production/Stable
Classifier: Environment :: Web Environment
Classifier: Framework :: Django
Classifier: Intended Audience :: Developers
Classifier: Natural Language :: English
Classifier: License :: OSI Approved :: BSD License
Classifier: Operating System :: OS Independent
Classifier: Programming Language :: Python
Classifier: Topic :: Utilities
